juxtematics/__init__.py
juxtematics/angle.py
juxtematics/calibration/calibrationHelper.py
juxtematics/calibration/calibrationPlane.py
juxtematics/calibration.py
juxtematics/circle_fitter.py
juxtematics/constants.py
juxtematics/exporter.py
juxtematics/filtering.py
juxtematics/human_profile.py
juxtematics/kinematics.py
juxtematics/ops.py
juxtematics/point.py
juxtematics/smoothing.py
juxtematics/types/human.py
juxtematics/types/point.py
juxtematics/utils.py
juxtematics-0.1.3.dist-info/LICENSE
juxtematics-0.1.3.dist-info/METADATA
juxtematics-0.1.3.dist-info/WHEEL
juxtematics-0.1.3.dist-info/RECORD
